hilbert/__init__.py
hilbert/algebra.py
hilbert/operators.py
hilbert/quantum.py
hilbert/spaces.py
hilbert/stock.py
hilbert/curves/__init__.py
hilbert/curves/base.py
hilbert/curves/lib.py
hilbert/curves/vectors.py
tests/__init__.py
tests/test_algebra.py
tests/test_curves.py
tests/test_spaces.py
tests/test_stock.py
hilbert_curve-1.0.dev4.dist-info/LICENSE
hilbert_curve-1.0.dev4.dist-info/METADATA
hilbert_curve-1.0.dev4.dist-info/WHEEL
hilbert_curve-1.0.dev4.dist-info/top_level.txt
hilbert_curve-1.0.dev4.dist-info/RECORD
